kube_module/__init__.py
kube_module/memory_check.py
kube_module-0.1.0.dist-info/METADATA
kube_module-0.1.0.dist-info/WHEEL
kube_module-0.1.0.dist-info/top_level.txt
kube_module-0.1.0.dist-info/RECORD
